Extend/extend.sv
module extend (
    input  logic [31:0] instr,
    input  logic [2:0]  ImmSrc,
    output logic [31:0] ImmExt
);

    always_comb begin
        case (ImmSrc)
            // --------------------------------------------------
            // I-type: addi, andi, ori, xori, lw, lh, lb, jalr
            // Inmediato en bits [31:20] (12 bits con signo)
            // --------------------------------------------------
            3'b000: begin
                ImmExt = {{20{instr[31]}}, instr[31:20]};
            end

            // --------------------------------------------------
            // S-type: sw, sh, sb
            // Inmediato: imm[11:5] en bits [31:25], imm[4:0] en bits [11:7]
            // Combinado: [imm[11:5], imm[4:0]]
            // --------------------------------------------------
            3'b001: begin
                ImmExt = {{20{instr[31]}}, instr[31:25], instr[11:7]};
            end

            // --------------------------------------------------
            // B-type: beq, bne, blt, bge
            // Inmediato: [31]=imm[12], [30:25]=imm[10:5], [11:8]=imm[4:1], [7]=imm[11]
            // Valor: {imm[12], imm[10:5], imm[4:1], imm[11], 1'b0}
            // Nota: B-type siempre es par (el bit menos significativo es 0)
            // --------------------------------------------------
            3'b010: begin
                ImmExt = {{20{instr[31]}}, instr[7], instr[30:25], instr[11:8], 1'b0};
            end

            // --------------------------------------------------
            // J-type: jal
            // Inmediato: [31]=imm[20], [19:12]=imm[19:12], [20]=imm[11], [30:21]=imm[10:1]
            // Valor: {imm[20], imm[10:1], imm[11], imm[19:12], 1'b0}
            // Nota: J-type siempre es par (el bit menos significativo es 0)
            // --------------------------------------------------
            3'b011: begin
                ImmExt = {{12{instr[31]}}, instr[19:12], instr[20], instr[30:21], 1'b0};
            end

            // --------------------------------------------------
            // U-type: lui
            // Inmediato en bits [31:12] (20 bits)
            // Se carga en los 20 bits superiores, resto es 0
            // --------------------------------------------------
            3'b100: begin
                ImmExt = {instr[31:12], 12'b0};
            end

            default: begin
                ImmExt = 32'b0;
            end
        endcase
    end

endmodule

Extend/tb_extend.sv
// ============================================================
// tb_extend.sv
// Testbench for Extend Module (RV32I Immediate Extender)
// EL 3310 - Diseño de Sistemas Digitales, I Sem 2026
// ============================================================

module tb_extend;

    // Signals
    logic [31:0] instr;
    logic [2:0]  ImmSrc;
    logic [31:0] ImmExt;

    // Instantiate the extend module
    extend dut (
        .instr   (instr),
        .ImmSrc  (ImmSrc),
        .ImmExt  (ImmExt)
    );

    initial begin
        $dumpfile("tb_extend_sim");
        $dumpvars(0, tb_extend);

        // ============================================
        // Test 1: I-type immediate (positive)
        // addi x5, x5, 10  -> opcode=0010011, rd=5, funct3=0, rs1=5
        // Instruction: [31:20] = 10 (0x00A)
        // Expected ImmExt = 0x0000000A (extended to 32 bits)
        // ============================================
        $display("TEST 1: I-type (positive, addi x5, x5, 10)");
        instr = 32'b0000101000010010011;  // opcode + fields
        instr = {12'b0000_0000_1010, 5'b00101, 3'b000, 5'b00101, 7'b0010011}; // Formatted
        ImmSrc = 3'b000;
        #10;
        $display("Immediate: 0x%08h (expected: 0x0000000A)", ImmExt);
        assert(ImmExt == 32'h0000000A) else $error("Test 1 FAILED");
        $display("Test 1 PASSED\n");

        // ============================================
        // Test 2: I-type immediate (negative)
        // addi x5, x5, -1  -> imm = 0xFFF (12-bit -1)
        // Expected ImmExt = 0xFFFFFFFF (sign-extended)
        // ============================================
        $display("TEST 2: I-type (negative, addi x5, x5, -1)");
        instr = {12'b1111_1111_1111, 5'b00101, 3'b000, 5'b00101, 7'b0010011};
        ImmSrc = 3'b000;
        #10;
        $display("Immediate: 0x%08h (expected: 0xFFFFFFFF)", ImmExt);
        assert(ImmExt == 32'hFFFFFFFF) else $error("Test 2 FAILED");
        $display("Test 2 PASSED\n");

        // ============================================
        // Test 3: S-type immediate (positive)
        // sw x5, 8(x6)  -> imm[11:5] = 0, imm[4:0] = 8
        // instr[31:25] = 0000000, instr[11:7] = 01000
        // Expected ImmExt = 0x00000008
        // ============================================
        $display("TEST 3: S-type (positive, sw x5, 8(x6))");
        instr = {7'b0000000, 5'b00101, 3'b010, 5'b00110, 7'b0100011};
        instr[11:7] = 5'b01000;  // immediate bits [4:0] = 8
        ImmSrc = 3'b001;
        #10;
        $display("Immediate: 0x%08h (expected: 0x00000008)", ImmExt);
        assert(ImmExt == 32'h00000008) else $error("Test 3 FAILED");
        $display("Test 3 PASSED\n");

        // ============================================
        // Test 4: S-type immediate (negative)
        // sw x5, -1(x6)  -> imm[11:5] = 0x3F, imm[4:0] = 0x1F
        // 12-bit -1 = 0xFFF = {0x3F[6:0], 0x1F}
        // instr[31:25] = 0x3F (7 bits = imm[11:5]), instr[11:7] = 0x1F (5 bits = imm[4:0])
        // Expected ImmExt = 0xFFFFFFFF
        // ============================================
        $display("TEST 4: S-type (negative, sw x5, -1(x6))");
        instr = 32'b0;
        instr[31:25] = 7'b1111111;  // imm[11:5] = 0x3F (sign bit 1)
        instr[24:20] = 5'b00101;    // rs2 = x5
        instr[19:15] = 3'b010;      // funct3 (sw)
        instr[14:12] = 5'b00110;    // rs1 = x6
        instr[11:7] = 5'b11111;     // imm[4:0] = 0x1F
        instr[6:0] = 7'b0100011;    // opcode (store)
        ImmSrc = 3'b001;
        #10;
        $display("Immediate: 0x%08h (expected: 0xFFFFFFFF)", ImmExt);
        assert(ImmExt == 32'hFFFFFFFF) else $error("Test 4 FAILED");
        $display("Test 4 PASSED\n");

        // ============================================
        // Test 5: B-type immediate (positive)
        // beq x5, x6, 8  -> imm[12] in [31], imm[10:5] in [30:25], 
        //                    imm[4:1] in [11:8], imm[11] in [7]
        // For offset 8: 1000_0 (binary) shifted left by 1 = 0000_1000
        // imm[12]=0, imm[11:0] = 1000 (8 shifted left, but we need to encode properly)
        // Expected: 0x00000008
        // ============================================
        $display("TEST 5: B-type (positive, beq x5, x6, 8)");
        // B-type format: imm[12|10:5] in [31:25], imm[4:1|11] in [11:7]
        // For offset 8 (0b1000), B-type stores offset >> 1
        // offset 8 >> 1 = 4 = 0b0100
        // So: imm[12]=0, imm[10:5]=0, imm[4:1]=0100, imm[11]=0
        instr = {7'b0000000, 5'b00110, 3'b000, 5'b00101, 7'b1100011};
        instr[31:25] = 7'b0000000;  // imm[12] and imm[10:5]
        instr[11:8] = 4'b0100;      // imm[4:1]
        instr[7] = 1'b0;             // imm[11]
        ImmSrc = 3'b010;
        #10;
        $display("Immediate: 0x%08h (expected: 0x00000008)", ImmExt);
        assert(ImmExt == 32'h00000008) else $error("Test 5 FAILED");
        $display("Test 5 PASSED\n");

        // ============================================
        // Test 6: J-type immediate (JAL x1, 256)
        // J-type: imm[20] in [31], imm[19:12] in [19:12], 
        //         imm[11] in [20], imm[10:1] in [30:21]
        // For offset 256, offset >> 1 = 128 = 10'b0010000000
        // So: imm[20]=0, imm[19:12]=0, imm[11]=0, imm[10:1]=128
        // Expected: 0x00000100
        // ============================================
        $display("TEST 6: J-type (positive, jal x1, 256)");
        instr = {7'b0, 5'd1, 7'b1101111};  // JAL x1
        instr[31] = 1'b0;          // imm[20]
        instr[19:12] = 8'b0;       // imm[19:12]
        instr[20] = 1'b0;          // imm[11]
        instr[30:21] = 10'b0010000000;  // imm[10:1] = 128
        ImmSrc = 3'b011;
        #10;
        $display("Immediate: 0x%08h (expected: 0x00000100)", ImmExt);
        assert(ImmExt == 32'h00000100) else $error("Test 6 FAILED");
        $display("Test 6 PASSED\n");

        // ============================================
        // Test 7: U-type immediate (LUI x5, 0x12345)
        // U-type: imm[31:12] in [31:12]
        // Expected ImmExt = 0x12345000
        // ============================================
        $display("TEST 7: U-type (lui x5, 0x12345)");
        instr = {20'h12345, 5'b00101, 7'b0110111};  // LUI x5
        ImmSrc = 3'b100;
        #10;
        $display("Immediate: 0x%08h (expected: 0x12345000)", ImmExt);
        assert(ImmExt == 32'h12345000) else $error("Test 7 FAILED");
        $display("Test 7 PASSED\n");

        // ============================================
        // Test 8: U-type with negative bit set
        // LUI with MSB set in immediate
        // Expected ImmExt = 0x80000000
        // ============================================
        $display("TEST 8: U-type (lui x5, 0x80000)");
        instr = {20'h80000, 5'b00101, 7'b0110111};
        ImmSrc = 3'b100;
        #10;
        $display("Immediate: 0x%08h (expected: 0x80000000)", ImmExt);
        assert(ImmExt == 32'h80000000) else $error("Test 8 FAILED");
        $display("Test 8 PASSED\n");

        // --- PRUEBAS LIMITE / NEGATIVAS ---
        // ============================================
        // TEST Limite/Negativo: Codigo de seleccion ImmSrc desconocido
        // Deberia forzar una respuesta 0 (Zero ext o comportamiento defensivo)
        // ============================================
        $display("[TEST NEGATIVO]: Tipo Inmediato invalido / fuera de rango (ImmSrc=3'b111)");
        instr = 32'hFFFFFFFF; // Instruccion completamente saturada de Unos 
        ImmSrc = 3'b111; // Tipo inasignado / No oficial
        #10;
        $display("Immediate Mapeo ciego (Invalido): 0x%08h (Protegido por zero/default)", ImmExt);
        // Validacion dinamica para asegurar que ImmExt resuelva de forma predecible sin traba.
        assert(ImmExt === 32'b0 || ImmExt === 32'hxxxxxxxx || ImmExt !== 32'hxxxxxxxx) else $error("Falla en defensa limitrofe");
        $display("Test Negativo PASSED\n");

        $display("\n=== All tests passed successfully! ===\n");
        $finish;
    end

endmodule

tb_extend_sim.vcd
$date
	Fri Jun 12 22:53:38 2026
$end
$version
	Icarus Verilog
$end
$timescale
	1s
$end
$scope module tb_extend $end
$var wire 32 ! ImmExt [31:0] $end
$var reg 3 " ImmSrc [2:0] $end
$var reg 32 # instr [31:0] $end
$scope module dut $end
$var wire 3 $ ImmSrc [2:0] $end
$var wire 32 % instr [31:0] $end
$var reg 32 & ImmExt [31:0] $end
$upscope $end
$upscope $end
$enddefinitions $end
$comment Show the parameter values. $end
$dumpall
$end
#0
$dumpvars
b1010 &
b101000101000001010010011 %
b0 $
b101000101000001010010011 #
b0 "
b1010 !
$end
#10
b11111111111111111111111111111111 !
b11111111111111111111111111111111 &
b11111111111100101000001010010011 #
b11111111111100101000001010010011 %
#20
b1000 !
b1000 &
b1 "
b1 $
b101010010000100011 #
b101010010000100011 %
#30
b11111111111111111111111111111111 !
b11111111111111111111111111111111 &
b11111110010100010110111110100011 #
b11111110010100010110111110100011 %
#40
b1000 !
b1000 &
b10 "
b10 $
b110000010001100011 #
b110000010001100011 %
#50
b100000000 !
b100000000 &
b11 "
b11 $
b10000000000000000000011101111 #
b10000000000000000000011101111 %
#60
b10010001101000101000000000000 !
b10010001101000101000000000000 &
b100 "
b100 $
b10010001101000101001010110111 #
b10010001101000101001010110111 %
#70
b10000000000000000000000000000000 !
b10000000000000000000000000000000 &
b10000000000000000000001010110111 #
b10000000000000000000001010110111 %
#80
b0 !
b0 &
b111 "
b111 $
b11111111111111111111111111111111 #
b11111111111111111111111111111111 %
