HazardUnit/hazard_unit.sv
// ============================================================
// Detecta y resuelve hazards en el pipeline RV32I de 5 etapas
//
// FORWARDING (EX hazard y MEM hazard):
//   ForwardA/B = 00 : usar dato del banco de registros (ID/EX)
//              = 10 : forwarding desde EX/MEM (resultado ALU)
//              = 01 : forwarding desde MEM/WB (writeback)
//
// STALL (load-use hazard):
//   Cuando la instrucción en EX es LOAD y su rd coincide con
//   rs1 o rs2 de la instrucción en ID → stall 1 ciclo
//
// FLUSH:
//   Cuando se toma un salto (PCSrc=1 resuelto en EX) →
//   vaciar IF/ID e ID/EX (insertar 2 NOPs)
// ============================================================
`timescale 1ns/1ps

module hazard_unit (
    // Fuentes de la instrucción en ID/EX
    input  logic [4:0] ID_EX_rs1,
    input  logic [4:0] ID_EX_rs2,
    input  logic       ID_EX_ResultSrc1,   // bit[0] de ResultSrc; 1 = LOAD
    input  logic [4:0] ID_EX_rd,

    // Destinos de EX/MEM y MEM/WB (para forwarding)
    input  logic [4:0] EX_MEM_rd,
    input  logic       EX_MEM_RegWrite,
    input  logic [4:0] MEM_WB_rd,
    input  logic       MEM_WB_RegWrite,

    // Rs de la instrucción en IF/ID (para stall)
    input  logic [4:0] IF_ID_rs1,
    input  logic [4:0] IF_ID_rs2,

    // Indicador de salto tomado (viene de la etapa EX)
    input  logic       PCSrc,

    // Salidas de forwarding
    output logic [1:0] ForwardA,  // mux para ALU entrada A
    output logic [1:0] ForwardB,  // mux para ALU entrada B

    // Control de stall / flush
    output logic       stall,      // congela IF/ID y PC
    output logic       flush_ID_EX // vacía ID/EX (burbuja por stall o salto)
);

    // ----------------------------------------------------------
    // Forwarding: prioridad EX/MEM > MEM/WB
    // ----------------------------------------------------------
    always_comb begin
        // Forward A
        if (EX_MEM_RegWrite && (EX_MEM_rd != 5'b0) && (EX_MEM_rd == ID_EX_rs1))
            ForwardA = 2'b10;   // desde EX/MEM
        else if (MEM_WB_RegWrite && (MEM_WB_rd != 5'b0) && (MEM_WB_rd == ID_EX_rs1))
            ForwardA = 2'b01;   // desde MEM/WB
        else
            ForwardA = 2'b00;   // sin forwarding

        // Forward B
        if (EX_MEM_RegWrite && (EX_MEM_rd != 5'b0) && (EX_MEM_rd == ID_EX_rs2))
            ForwardB = 2'b10;
        else if (MEM_WB_RegWrite && (MEM_WB_rd != 5'b0) && (MEM_WB_rd == ID_EX_rs2))
            ForwardB = 2'b01;
        else
            ForwardB = 2'b00;
    end

    // ----------------------------------------------------------
    // Detección de load-use hazard
    // LOAD: ResultSrc[0] == 1 (2'b01)
    // ----------------------------------------------------------
    logic load_use_hazard;
    assign load_use_hazard = ID_EX_ResultSrc1 &&
                             ((ID_EX_rd == IF_ID_rs1) || (ID_EX_rd == IF_ID_rs2)) &&
                             (ID_EX_rd != 5'b0);

    // ----------------------------------------------------------
    // Stall: congelar PC e IF/ID, insertar burbuja en ID/EX
    // Flush: cuando el salto se resuelve en EX (PCSrc=1)
    //        se vacían IF/ID e ID/EX (2 instrucciones fetched de más)
    // ----------------------------------------------------------
    assign stall      = load_use_hazard;
    assign flush_ID_EX = load_use_hazard || PCSrc;

endmodule

HazardUnit/tb_hazard_unit.sv
// ============================================================
// tb_hazard_unit.sv
// Testbench para la unidad de detección y resolución de hazards
// ============================================================
`timescale 1ns/1ps

module tb_hazard_unit;
    // Señales de entrada
    logic [4:0] ID_EX_rs1, ID_EX_rs2, ID_EX_rd;
    logic       ID_EX_ResultSrc1;
    logic [4:0] EX_MEM_rd, MEM_WB_rd;
    logic       EX_MEM_RegWrite, MEM_WB_RegWrite;
    logic [4:0] IF_ID_rs1, IF_ID_rs2;
    logic       PCSrc;

    // Señales de salida
    logic [1:0] ForwardA, ForwardB;
    logic       stall, flush_ID_EX;

    // Variables de prueba
    integer test_pass = 0, test_fail = 0;

    // Instancia de DUT
    hazard_unit dut (
        .ID_EX_rs1      (ID_EX_rs1),
        .ID_EX_rs2      (ID_EX_rs2),
        .ID_EX_ResultSrc1(ID_EX_ResultSrc1),
        .ID_EX_rd       (ID_EX_rd),
        .EX_MEM_rd      (EX_MEM_rd),
        .EX_MEM_RegWrite(EX_MEM_RegWrite),
        .MEM_WB_rd      (MEM_WB_rd),
        .MEM_WB_RegWrite(MEM_WB_RegWrite),
        .IF_ID_rs1      (IF_ID_rs1),
        .IF_ID_rs2      (IF_ID_rs2),
        .PCSrc          (PCSrc),
        .ForwardA       (ForwardA),
        .ForwardB       (ForwardB),
        .stall          (stall),
        .flush_ID_EX    (flush_ID_EX)
    );

    // Task para verificar resultados
    task automatic check_test(
        input string test_name,
        input logic [1:0] exp_fwdA,
        input logic [1:0] exp_fwdB,
        input logic exp_stall,
        input logic exp_flush
    );
        if ((ForwardA === exp_fwdA) && (ForwardB === exp_fwdB) && 
            (stall === exp_stall) && (flush_ID_EX === exp_flush)) begin
            $display("[PASS] %s", test_name);
            test_pass++;
        end else begin
            $display("[FAIL] %s", test_name);
            $display("       Expected: ForwardA=%b, ForwardB=%b, stall=%b, flush=%b",
                     exp_fwdA, exp_fwdB, exp_stall, exp_flush);
            $display("       Got:      ForwardA=%b, ForwardB=%b, stall=%b, flush=%b",
                     ForwardA, ForwardB, stall, flush_ID_EX);
            test_fail++;
        end
    endtask

    initial begin
        $dumpfile("tb_hazard_unit.vcd");
        $dumpvars(0, tb_hazard_unit);

        $display("============================================================");
        $display("  TESTBENCH: Hazard Unit");
        $display("============================================================\n");

        // ============================================================
        // Prueba 1: Sin hazard (estado idle)
        // ============================================================
        $display("=== Prueba 1: Sin hazard ===");
        ID_EX_rs1 = 5'b00000; ID_EX_rs2 = 5'b00000; ID_EX_rd = 5'b00000;
        ID_EX_ResultSrc1 = 1'b0;
        EX_MEM_rd = 5'b00000; EX_MEM_RegWrite = 1'b0;
        MEM_WB_rd = 5'b00000; MEM_WB_RegWrite = 1'b0;
        IF_ID_rs1 = 5'b00000; IF_ID_rs2 = 5'b00000;
        PCSrc = 1'b0;
        #1;
        check_test("No hazard", 2'b00, 2'b00, 1'b0, 1'b0);

        // ============================================================
        // Prueba 2: Forwarding desde EX/MEM para rs1
        // ============================================================
        $display("\n=== Prueba 2: Forwarding EX/MEM -> rs1 ===");
        ID_EX_rs1 = 5'd5;  // Lee de x5
        ID_EX_rs2 = 5'd6;  // Lee de x6
        ID_EX_rd = 5'd1;
        ID_EX_ResultSrc1 = 1'b0;  // No es LOAD
        EX_MEM_rd = 5'd5;  // x5 es el destino
        EX_MEM_RegWrite = 1'b1;
        MEM_WB_rd = 5'b00000;
        MEM_WB_RegWrite = 1'b0;
        IF_ID_rs1 = 5'b00000;
        IF_ID_rs2 = 5'b00000;
        PCSrc = 1'b0;
        #1;
        check_test("Forward EX/MEM to rs1", 2'b10, 2'b00, 1'b0, 1'b0);

        // ============================================================
        // Prueba 3: Forwarding desde EX/MEM para rs2
        // ============================================================
        $display("\n=== Prueba 3: Forwarding EX/MEM -> rs2 ===");
        ID_EX_rs1 = 5'd4;
        ID_EX_rs2 = 5'd5;  // Lee de x5
        ID_EX_rd = 5'd1;
        EX_MEM_rd = 5'd5;  // x5 es el destino
        EX_MEM_RegWrite = 1'b1;
        MEM_WB_rd = 5'b00000;
        MEM_WB_RegWrite = 1'b0;
        #1;
        check_test("Forward EX/MEM to rs2", 2'b00, 2'b10, 1'b0, 1'b0);

        // ============================================================
        // Prueba 4: Forwarding desde MEM/WB (cuando no hay EX/MEM)
        // ============================================================
        $display("\n=== Prueba 4: Forwarding MEM/WB ===");
        ID_EX_rs1 = 5'd3;
        ID_EX_rs2 = 5'd4;
        ID_EX_rd = 5'd1;
        EX_MEM_rd = 5'b00000;  // x0 no escribe
        EX_MEM_RegWrite = 1'b0;
        MEM_WB_rd = 5'd3;  // x3 es el destino en MEM/WB
        MEM_WB_RegWrite = 1'b1;
        #1;
        check_test("Forward MEM/WB to rs1", 2'b01, 2'b00, 1'b0, 1'b0);

        // ============================================================
        // Prueba 5: Prioridad EX/MEM > MEM/WB
        // ============================================================
        $display("\n=== Prueba 5: Prioridad EX/MEM > MEM/WB ===");
        ID_EX_rs1 = 5'd7;
        ID_EX_rs2 = 5'b00000;
        EX_MEM_rd = 5'd7;
        EX_MEM_RegWrite = 1'b1;
        MEM_WB_rd = 5'd7;  // Mismo registro en ambas etapas
        MEM_WB_RegWrite = 1'b1;
        #1;
        // Debe elegir EX/MEM (2'b10) en lugar de MEM/WB (2'b01)
        check_test("Priority EX/MEM over MEM/WB", 2'b10, 2'b00, 1'b0, 1'b0);

        // ============================================================
        // Prueba 6: Load-use hazard (stall)
        // ============================================================
        $display("\n=== Prueba 6: Load-use hazard ===");
        ID_EX_ResultSrc1 = 1'b1;  // Es LOAD
        ID_EX_rd = 5'd8;  // x8 es el destino de la LOAD
        ID_EX_rs1 = 5'b00000;
        ID_EX_rs2 = 5'b00000;
        EX_MEM_rd = 5'b00000;
        EX_MEM_RegWrite = 1'b0;
        MEM_WB_rd = 5'b00000;
        MEM_WB_RegWrite = 1'b0;
        IF_ID_rs1 = 5'd8;  // Próxima instr usa x8 (rs1)
        IF_ID_rs2 = 5'b00000;
        PCSrc = 1'b0;
        #1;
        check_test("Load-use hazard (stall)", 2'b00, 2'b00, 1'b1, 1'b1);

        // ============================================================
        // Prueba 7: Load-use hazard con rs2
        // ============================================================
        $display("\n=== Prueba 7: Load-use hazard (rs2) ===");
        IF_ID_rs1 = 5'b00000;
        IF_ID_rs2 = 5'd8;  // Próxima instr usa x8 (rs2)
        #1;
        check_test("Load-use hazard (rs2)", 2'b00, 2'b00, 1'b1, 1'b1);

        // ============================================================
        // Prueba 8: No stall si rd=x0
        // ============================================================
        $display("\n=== Prueba 8: No stall si rd=x0 ===");
        ID_EX_rd = 5'b00000;  // x0 nunca genera stall
        ID_EX_ResultSrc1 = 1'b1;  // Es LOAD
        IF_ID_rs1 = 5'b00000;
        IF_ID_rs2 = 5'b00000;
        #1;
        check_test("No stall for x0", 2'b00, 2'b00, 1'b0, 1'b0);

        // ============================================================
        // Prueba 9: Flush por branch/jump (PCSrc=1)
        // ============================================================
        $display("\n=== Prueba 9: Flush por branch ===");
        ID_EX_ResultSrc1 = 1'b0;
        ID_EX_rd = 5'd1;
        PCSrc = 1'b1;  // Branch tomado
        IF_ID_rs1 = 5'b00000;
        IF_ID_rs2 = 5'b00000;
        #1;
        check_test("Flush on branch", 2'b00, 2'b00, 1'b0, 1'b1);

        // ============================================================
        // Prueba 10: x0 no genera forwarding
        // ============================================================
        $display("\n=== Prueba 10: x0 no genera forwarding ===");
        ID_EX_rs1 = 5'b00000;
        ID_EX_rs2 = 5'b00000;
        EX_MEM_rd = 5'b00000;  // x0
        EX_MEM_RegWrite = 1'b1;
        MEM_WB_rd = 5'b00000;
        MEM_WB_RegWrite = 1'b0;
        PCSrc = 1'b0;
        #1;
        check_test("x0 never forwards", 2'b00, 2'b00, 1'b0, 1'b0);

        // ============================================================
        // Resumen
        // ============================================================
        $display("\n============================================================");
        $display("  RESUMEN");
        $display("============================================================");
        $display("  Tests PASS: %0d", test_pass);
        $display("  Tests FAIL: %0d", test_fail);
        if (test_fail == 0)
            $display("  RESULTADO: EXITO TOTAL");
        else
            $display("  RESULTADO: HAY ERRORES");
        $display("============================================================\n");
        $finish;
    end
endmodule

tb_hazard_unit.vcd
$date
	Sun Jun  7 21:08:44 2026
$end
$version
	Icarus Verilog
$end
$timescale
	1ps
$end
$scope module tb_hazard_unit $end
$var wire 1 ! stall $end
$var wire 1 " flush_ID_EX $end
$var wire 2 # ForwardB [1:0] $end
$var wire 2 $ ForwardA [1:0] $end
$var reg 1 % EX_MEM_RegWrite $end
$var reg 5 & EX_MEM_rd [4:0] $end
$var reg 1 ' ID_EX_ResultSrc1 $end
$var reg 5 ( ID_EX_rd [4:0] $end
$var reg 5 ) ID_EX_rs1 [4:0] $end
$var reg 5 * ID_EX_rs2 [4:0] $end
$var reg 5 + IF_ID_rs1 [4:0] $end
$var reg 5 , IF_ID_rs2 [4:0] $end
$var reg 1 - MEM_WB_RegWrite $end
$var reg 5 . MEM_WB_rd [4:0] $end
$var reg 1 / PCSrc $end
$var integer 32 0 test_fail [31:0] $end
$var integer 32 1 test_pass [31:0] $end
$scope module dut $end
$var wire 1 % EX_MEM_RegWrite $end
$var wire 5 2 EX_MEM_rd [4:0] $end
$var wire 1 ' ID_EX_ResultSrc1 $end
$var wire 5 3 ID_EX_rd [4:0] $end
$var wire 5 4 ID_EX_rs1 [4:0] $end
$var wire 5 5 ID_EX_rs2 [4:0] $end
$var wire 5 6 IF_ID_rs1 [4:0] $end
$var wire 5 7 IF_ID_rs2 [4:0] $end
$var wire 1 - MEM_WB_RegWrite $end
$var wire 5 8 MEM_WB_rd [4:0] $end
$var wire 1 / PCSrc $end
$var wire 1 " flush_ID_EX $end
$var wire 1 9 load_use_hazard $end
$var wire 1 ! stall $end
$var reg 2 : ForwardA [1:0] $end
$var reg 2 ; ForwardB [1:0] $end
$upscope $end
$scope task check_test $end
$upscope $end
$upscope $end
$enddefinitions $end
$comment Show the parameter values. $end
$dumpall
$end
#0
$dumpvars
b0 ;
b0 :
09
b0 8
b0 7
b0 6
b0 5
b0 4
b0 3
b0 2
b0 1
b0 0
0/
b0 .
0-
b0 ,
b0 +
b0 *
b0 )
b0 (
0'
b0 &
0%
b0 $
b0 #
0"
0!
$end
#1000
b10 $
b10 :
1%
b101 &
b101 2
b1 (
b1 3
b110 *
b110 5
b101 )
b101 4
b1 1
#2000
b10 #
b10 ;
b0 $
b0 :
b101 *
b101 5
b100 )
b100 4
b10 1
#3000
b0 #
b0 ;
b1 $
b1 :
1-
b11 .
b11 8
0%
b0 &
b0 2
b100 *
b100 5
b11 )
b11 4
b11 1
#4000
b10 $
b10 :
b111 .
b111 8
1%
b111 &
b111 2
b0 *
b0 5
b111 )
b111 4
b100 1
#5000
1"
1!
19
b0 $
b0 :
b1000 +
b1000 6
0-
b0 .
b0 8
0%
b0 &
b0 2
b0 )
b0 4
b1000 (
b1000 3
1'
b101 1
#6000
b1000 ,
b1000 7
b0 +
b0 6
b110 1
#7000
0"
0!
09
b0 ,
b0 7
b0 (
b0 3
b111 1
#8000
1"
1/
b1 (
b1 3
0'
b1000 1
#9000
0"
0/
1%
b1001 1
#10000
b1010 1
