HazardUnit/hazard_unit.sv
// ============================================================
// Detecta y resuelve hazards en el pipeline RV32I de 5 etapas
//
// FORWARDING (EX hazard y MEM hazard):
//   ForwardA/B = 00 : usar dato del banco de registros (ID/EX)
//              = 10 : forwarding desde EX/MEM (resultado ALU)
//              = 01 : forwarding desde MEM/WB (writeback)
//
// STALL (load-use hazard):
//   Cuando la instrucción en EX es LOAD y su rd coincide con
//   rs1 o rs2 de la instrucción en ID → stall 1 ciclo
//
// FLUSH:
//   Cuando se toma un salto (PCSrc=1 resuelto en EX) →
//   vaciar IF/ID e ID/EX (insertar 2 NOPs)
// ============================================================
`timescale 1ns/1ps

module hazard_unit (
    // Fuentes de la instrucción en ID/EX
    input  logic [4:0] ID_EX_rs1,
    input  logic [4:0] ID_EX_rs2,
    input  logic       ID_EX_ResultSrc1,   // bit[0] de ResultSrc; 1 = LOAD
    input  logic [4:0] ID_EX_rd,

    // Destinos de EX/MEM y MEM/WB (para forwarding)
    input  logic [4:0] EX_MEM_rd,
    input  logic       EX_MEM_RegWrite,
    input  logic [4:0] MEM_WB_rd,
    input  logic       MEM_WB_RegWrite,

    // Rs de la instrucción en IF/ID (para stall)
    input  logic [4:0] IF_ID_rs1,
    input  logic [4:0] IF_ID_rs2,

    // Indicador de salto tomado (viene de la etapa EX)
    input  logic       PCSrc,

    // Salidas de forwarding
    output logic [1:0] ForwardA,  // mux para ALU entrada A
    output logic [1:0] ForwardB,  // mux para ALU entrada B

    // Control de stall / flush
    output logic       stall,      // congela IF/ID y PC
    output logic       flush_ID_EX // vacía ID/EX (burbuja por stall o salto)
);

    // ----------------------------------------------------------
    // Forwarding: prioridad EX/MEM > MEM/WB
    // ----------------------------------------------------------
    always_comb begin
        // Forward A
        if (EX_MEM_RegWrite && (EX_MEM_rd != 5'b0) && (EX_MEM_rd == ID_EX_rs1))
            ForwardA = 2'b10;   // desde EX/MEM
        else if (MEM_WB_RegWrite && (MEM_WB_rd != 5'b0) && (MEM_WB_rd == ID_EX_rs1))
            ForwardA = 2'b01;   // desde MEM/WB
        else
            ForwardA = 2'b00;   // sin forwarding

        // Forward B
        if (EX_MEM_RegWrite && (EX_MEM_rd != 5'b0) && (EX_MEM_rd == ID_EX_rs2))
            ForwardB = 2'b10;
        else if (MEM_WB_RegWrite && (MEM_WB_rd != 5'b0) && (MEM_WB_rd == ID_EX_rs2))
            ForwardB = 2'b01;
        else
            ForwardB = 2'b00;
    end

    // ----------------------------------------------------------
    // Detección de load-use hazard
    // LOAD: ResultSrc[0] == 1 (2'b01)
    // ----------------------------------------------------------
    logic load_use_hazard;
    assign load_use_hazard = ID_EX_ResultSrc1 &&
                             ((ID_EX_rd == IF_ID_rs1) || (ID_EX_rd == IF_ID_rs2)) &&
                             (ID_EX_rd != 5'b0);

    // ----------------------------------------------------------
    // Stall: congelar PC e IF/ID, insertar burbuja en ID/EX
    // Flush: cuando el salto se resuelve en EX (PCSrc=1)
    //        se vacían IF/ID e ID/EX (2 instrucciones fetched de más)
    // ----------------------------------------------------------
    assign stall      = load_use_hazard;
    assign flush_ID_EX = load_use_hazard || PCSrc;

endmodule

HazardUnit/tb_hazard_unit.sv
// ============================================================
// tb_hazard_unit.sv
// Testbench para la unidad de detección y resolución de hazards
//
// Para cada prueba se muestra:
//   - El escenario de pipeline que se está modelando
//   - Los valores de entrada aplicados
//   - Las salidas obtenidas vs esperadas
// ============================================================
`timescale 1ns/1ps

module tb_hazard_unit;

    // -------------------------------------------------------
    // Señales
    // -------------------------------------------------------
    logic [4:0] ID_EX_rs1, ID_EX_rs2, ID_EX_rd;
    logic       ID_EX_ResultSrc1;
    logic [4:0] EX_MEM_rd,  MEM_WB_rd;
    logic       EX_MEM_RegWrite, MEM_WB_RegWrite;
    logic [4:0] IF_ID_rs1, IF_ID_rs2;
    logic       PCSrc;

    logic [1:0] ForwardA, ForwardB;
    logic       stall, flush_ID_EX;

    integer test_pass = 0, test_fail = 0;

    // -------------------------------------------------------
    // DUT
    // -------------------------------------------------------
    hazard_unit dut (
        .ID_EX_rs1      (ID_EX_rs1),
        .ID_EX_rs2      (ID_EX_rs2),
        .ID_EX_ResultSrc1(ID_EX_ResultSrc1),
        .ID_EX_rd       (ID_EX_rd),
        .EX_MEM_rd      (EX_MEM_rd),
        .EX_MEM_RegWrite(EX_MEM_RegWrite),
        .MEM_WB_rd      (MEM_WB_rd),
        .MEM_WB_RegWrite(MEM_WB_RegWrite),
        .IF_ID_rs1      (IF_ID_rs1),
        .IF_ID_rs2      (IF_ID_rs2),
        .PCSrc          (PCSrc),
        .ForwardA       (ForwardA),
        .ForwardB       (ForwardB),
        .stall          (stall),
        .flush_ID_EX    (flush_ID_EX)
    );

    // -------------------------------------------------------
    // Tarea de verificación: imprime contexto y resultado
    // -------------------------------------------------------
    task automatic check_test(
        input string  test_name,
        input string  scenario,
        input logic [1:0] exp_fwdA,
        input logic [1:0] exp_fwdB,
        input logic exp_stall,
        input logic exp_flush
    );
        logic ok;
        ok = (ForwardA === exp_fwdA) && (ForwardB === exp_fwdB) &&
             (stall   === exp_stall) && (flush_ID_EX === exp_flush);

        $display("  Escenario : %s", scenario);
        $display("  Entradas  : ID_EX_rs1=x%0d  rs2=x%0d  rd=x%0d  ResultSrc1=%b",
                 ID_EX_rs1, ID_EX_rs2, ID_EX_rd, ID_EX_ResultSrc1);
        $display("              EX_MEM_rd=x%0d(RW=%b)  MEM_WB_rd=x%0d(RW=%b)  PCSrc=%b",
                 EX_MEM_rd, EX_MEM_RegWrite, MEM_WB_rd, MEM_WB_RegWrite, PCSrc);
        $display("              IF_ID_rs1=x%0d  IF_ID_rs2=x%0d",
                 IF_ID_rs1, IF_ID_rs2);
        $display("  Esperado  : FwdA=%b  FwdB=%b  stall=%b  flush=%b",
                 exp_fwdA, exp_fwdB, exp_stall, exp_flush);
        $display("  Obtenido  : FwdA=%b  FwdB=%b  stall=%b  flush=%b",
                 ForwardA, ForwardB, stall, flush_ID_EX);

        if (ok) begin
            $display("  [PASS] %s\n", test_name);
            test_pass++;
        end else begin
            $display("  [FAIL] %s\n", test_name);
            test_fail++;
        end
    endtask

    // -------------------------------------------------------
    // Tarea auxiliar: pone todo en estado "sin hazard"
    // -------------------------------------------------------
    task automatic set_idle();
        ID_EX_rs1      = 5'd0;  ID_EX_rs2      = 5'd0;  ID_EX_rd  = 5'd0;
        ID_EX_ResultSrc1 = 1'b0;
        EX_MEM_rd      = 5'd0;  EX_MEM_RegWrite = 1'b0;
        MEM_WB_rd      = 5'd0;  MEM_WB_RegWrite = 1'b0;
        IF_ID_rs1      = 5'd0;  IF_ID_rs2       = 5'd0;
        PCSrc          = 1'b0;
    endtask

    // -------------------------------------------------------
    // Pruebas
    // -------------------------------------------------------
    initial begin
        $dumpfile("tb_hazard_unit.vcd");
        $dumpvars(0, tb_hazard_unit);

        $display("============================================================");
        $display("  TESTBENCH: Hazard Unit");
        $display("  Muestra: escenario | entradas aplicadas | salidas");
        $display("============================================================\n");

        // ----------------------------------------------------------
        // P1: Sin ningún hazard → no forwarding, no stall, no flush
        // ----------------------------------------------------------
        $display("=== Prueba 1: Sin hazard (estado idle) ===");
        set_idle(); #1;
        check_test(
            "No hazard",
            "Instrucciones independientes, registros distintos",
            2'b00, 2'b00, 1'b0, 1'b0
        );

        // ----------------------------------------------------------
        // P2: EX hazard en rs1
        //   EX: add x5, x1, x2   → escribe x5 (en EX/MEM)
        //   ID: add x3, x5, x4   → lee x5 (rs1) → forward desde EX/MEM
        // ----------------------------------------------------------
        $display("=== Prueba 2: Forwarding EX/MEM → rs1 ===");
        set_idle();
        ID_EX_rs1 = 5'd5;   // instrucción en EX lee x5 como rs1
        ID_EX_rs2 = 5'd4;
        EX_MEM_rd = 5'd5;   EX_MEM_RegWrite = 1'b1;  // x5 está en EX/MEM
        #1;
        check_test(
            "Forward EX/MEM to rs1",
            "EX/MEM.rd==ID_EX.rs1, EX/MEM.RegWrite=1 → ForwardA=10",
            2'b10, 2'b00, 1'b0, 1'b0
        );

        // ----------------------------------------------------------
        // P3: EX hazard en rs2
        //   EX: sw x5, 0(x6)  → lee x5 como rs2
        //   MEM: add x5, ...  → x5 está en EX/MEM
        // ----------------------------------------------------------
        $display("=== Prueba 3: Forwarding EX/MEM → rs2 ===");
        set_idle();
        ID_EX_rs1 = 5'd4;
        ID_EX_rs2 = 5'd5;   // instrucción en EX lee x5 como rs2
        EX_MEM_rd = 5'd5;   EX_MEM_RegWrite = 1'b1;
        #1;
        check_test(
            "Forward EX/MEM to rs2",
            "EX/MEM.rd==ID_EX.rs2, EX/MEM.RegWrite=1 → ForwardB=10",
            2'b00, 2'b10, 1'b0, 1'b0
        );

        // ----------------------------------------------------------
        // P4: MEM hazard en rs1 (x5 ya salió de EX/MEM, está en MEM/WB)
        // ----------------------------------------------------------
        $display("=== Prueba 4: Forwarding MEM/WB → rs1 ===");
        set_idle();
        ID_EX_rs1 = 5'd3;
        EX_MEM_rd = 5'd0;   EX_MEM_RegWrite = 1'b0;  // nadie en EX/MEM sobre x3
        MEM_WB_rd = 5'd3;   MEM_WB_RegWrite = 1'b1;  // x3 está en MEM/WB
        #1;
        check_test(
            "Forward MEM/WB to rs1",
            "MEM_WB.rd==ID_EX.rs1, MEM_WB.RegWrite=1 → ForwardA=01",
            2'b01, 2'b00, 1'b0, 1'b0
        );

        // ----------------------------------------------------------
        // P5: MEM hazard en rs2
        // ----------------------------------------------------------
        $display("=== Prueba 5: Forwarding MEM/WB → rs2 ===");
        set_idle();
        ID_EX_rs2 = 5'd6;
        EX_MEM_rd = 5'd0;   EX_MEM_RegWrite = 1'b0;
        MEM_WB_rd = 5'd6;   MEM_WB_RegWrite = 1'b1;
        #1;
        check_test(
            "Forward MEM/WB to rs2",
            "MEM_WB.rd==ID_EX.rs2, MEM_WB.RegWrite=1 → ForwardB=01",
            2'b00, 2'b01, 1'b0, 1'b0
        );

        // ----------------------------------------------------------
        // P6: Prioridad EX/MEM > MEM/WB (mismo registro en ambas etapas)
        //   Ocurre si dos instrucciones consecutivas escriben el mismo rd
        // ----------------------------------------------------------
        $display("=== Prueba 6: Prioridad EX/MEM sobre MEM/WB (mismo rd) ===");
        set_idle();
        ID_EX_rs1 = 5'd7;
        EX_MEM_rd = 5'd7;   EX_MEM_RegWrite = 1'b1;  // valor más nuevo
        MEM_WB_rd = 5'd7;   MEM_WB_RegWrite = 1'b1;  // valor más viejo
        #1;
        check_test(
            "Priority EX/MEM over MEM/WB",
            "Mismo rd en EX/MEM y MEM/WB → se elige EX/MEM (ForwardA=10)",
            2'b10, 2'b00, 1'b0, 1'b0
        );

        // ----------------------------------------------------------
        // P7: Load-use hazard por rs1
        //   EX: lw x8, 0(x1)   → ID_EX_rd=x8, ResultSrc1=1
        //   ID: add x3, x8, x2 → IF_ID_rs1=x8 → stall 1 ciclo
        // ----------------------------------------------------------
        $display("=== Prueba 7: Load-use hazard (rs1) ===");
        set_idle();
        ID_EX_ResultSrc1 = 1'b1;  // instrucción en EX es LOAD
        ID_EX_rd  = 5'd8;         // LOAD escribe en x8
        IF_ID_rs1 = 5'd8;         // siguiente instrucción necesita x8
        #1;
        check_test(
            "Load-use hazard via rs1",
            "LOAD x8 en EX, siguiente instruccion lee rs1=x8 → stall+flush",
            2'b00, 2'b00, 1'b1, 1'b1
        );

        // ----------------------------------------------------------
        // P8: Load-use hazard por rs2
        //   EX: lw x8, 4(x1)   → ID_EX_rd=x8
        //   ID: sw x8, 8(x2)   → IF_ID_rs2=x8 → stall
        // ----------------------------------------------------------
        $display("=== Prueba 8: Load-use hazard (rs2) ===");
        set_idle();
        ID_EX_ResultSrc1 = 1'b1;
        ID_EX_rd  = 5'd8;
        IF_ID_rs2 = 5'd8;         // necesita x8 en rs2
        #1;
        check_test(
            "Load-use hazard via rs2",
            "LOAD x8 en EX, siguiente instruccion lee rs2=x8 → stall+flush",
            2'b00, 2'b00, 1'b1, 1'b1
        );

        // ----------------------------------------------------------
        // P9: No stall si rd == x0 aunque ResultSrc1=1
        //   x0 es siempre cero, nunca genera hazard real
        // ----------------------------------------------------------
        $display("=== Prueba 9: No stall si LOAD rd=x0 ===");
        set_idle();
        ID_EX_ResultSrc1 = 1'b1;
        ID_EX_rd  = 5'd0;         // destino x0: no importa
        IF_ID_rs1 = 5'd0;
        IF_ID_rs2 = 5'd0;
        #1;
        check_test(
            "No stall for x0 destination",
            "LOAD a x0 nunca produce stall (x0 siempre es 0)",
            2'b00, 2'b00, 1'b0, 1'b0
        );

        // ----------------------------------------------------------
        // P10: Flush por branch/jump resuelto en EX (PCSrc=1)
        //   Se deben anular las 2 instrucciones fetched de más
        // ----------------------------------------------------------
        $display("=== Prueba 10: Flush por branch tomado (PCSrc=1) ===");
        set_idle();
        PCSrc = 1'b1;   // salto resuelto → flush
        #1;
        check_test(
            "Flush on branch taken",
            "PCSrc=1 → vaciar IF/ID e ID/EX (2 NOPs)",
            2'b00, 2'b00, 1'b0, 1'b1
        );

        // ----------------------------------------------------------
        // P11: Load-use + PCSrc simultáneos
        //   Stall tiene precedencia; flush también activo
        // ----------------------------------------------------------
        $display("=== Prueba 11: Load-use hazard + PCSrc simultáneos ===");
        set_idle();
        ID_EX_ResultSrc1 = 1'b1;
        ID_EX_rd  = 5'd9;
        IF_ID_rs1 = 5'd9;
        PCSrc     = 1'b1;
        #1;
        check_test(
            "Load-use + branch simultaneous",
            "Ambas condiciones activas → stall=1, flush=1",
            2'b00, 2'b00, 1'b1, 1'b1
        );

        // ----------------------------------------------------------
        // P12: Forwarding no activa cuando RegWrite=0
        // ----------------------------------------------------------
        $display("=== Prueba 12: Sin forwarding si RegWrite=0 ===");
        set_idle();
        ID_EX_rs1 = 5'd4;
        EX_MEM_rd = 5'd4;   EX_MEM_RegWrite = 1'b0;  // no escribe
        MEM_WB_rd = 5'd4;   MEM_WB_RegWrite = 1'b0;  // no escribe
        #1;
        check_test(
            "No forward when RegWrite=0",
            "EX/MEM y MEM/WB tienen el mismo rd pero RegWrite=0 → sin forward",
            2'b00, 2'b00, 1'b0, 1'b0
        );

        // ----------------------------------------------------------
        // P13: Forwarding doble (rs1 de MEM/WB, rs2 de EX/MEM)
        // ----------------------------------------------------------
        $display("=== Prueba 13: Forwarding doble (rs1 y rs2 distintos) ===");
        set_idle();
        ID_EX_rs1 = 5'd3;   // rs1 viene de MEM/WB
        ID_EX_rs2 = 5'd5;   // rs2 viene de EX/MEM
        EX_MEM_rd = 5'd5;   EX_MEM_RegWrite = 1'b1;
        MEM_WB_rd = 5'd3;   MEM_WB_RegWrite = 1'b1;
        #1;
        check_test(
            "Double forward: rs1 from MEM/WB, rs2 from EX/MEM",
            "FwdA=01 (MEM/WB→rs1) y FwdB=10 (EX/MEM→rs2) simultáneos",
            2'b01, 2'b10, 1'b0, 1'b0
        );

        // ----------------------------------------------------------
        // Resumen
        // ----------------------------------------------------------
        $display("============================================================");
        $display("  RESUMEN");
        $display("============================================================");
        $display("  Tests PASS: %0d", test_pass);
        $display("  Tests FAIL: %0d", test_fail);
        if (test_fail == 0)
            $display("  RESULTADO: EXITO TOTAL");
        else
            $display("  RESULTADO: HAY ERRORES");
        $display("============================================================\n");
        $finish;
    end

endmodule

tb_hazard_unit.vcd
$date
	Fri Jun 12 22:53:38 2026
$end
$version
	Icarus Verilog
$end
$timescale
	1ps
$end
$scope module tb_hazard_unit $end
$var wire 1 ! stall $end
$var wire 1 " flush_ID_EX $end
$var wire 2 # ForwardB [1:0] $end
$var wire 2 $ ForwardA [1:0] $end
$var reg 1 % EX_MEM_RegWrite $end
$var reg 5 & EX_MEM_rd [4:0] $end
$var reg 1 ' ID_EX_ResultSrc1 $end
$var reg 5 ( ID_EX_rd [4:0] $end
$var reg 5 ) ID_EX_rs1 [4:0] $end
$var reg 5 * ID_EX_rs2 [4:0] $end
$var reg 5 + IF_ID_rs1 [4:0] $end
$var reg 5 , IF_ID_rs2 [4:0] $end
$var reg 1 - MEM_WB_RegWrite $end
$var reg 5 . MEM_WB_rd [4:0] $end
$var reg 1 / PCSrc $end
$var integer 32 0 test_fail [31:0] $end
$var integer 32 1 test_pass [31:0] $end
$scope module dut $end
$var wire 1 % EX_MEM_RegWrite $end
$var wire 5 2 EX_MEM_rd [4:0] $end
$var wire 1 ' ID_EX_ResultSrc1 $end
$var wire 5 3 ID_EX_rd [4:0] $end
$var wire 5 4 ID_EX_rs1 [4:0] $end
$var wire 5 5 ID_EX_rs2 [4:0] $end
$var wire 5 6 IF_ID_rs1 [4:0] $end
$var wire 5 7 IF_ID_rs2 [4:0] $end
$var wire 1 - MEM_WB_RegWrite $end
$var wire 5 8 MEM_WB_rd [4:0] $end
$var wire 1 / PCSrc $end
$var wire 1 " flush_ID_EX $end
$var wire 1 9 load_use_hazard $end
$var wire 1 ! stall $end
$var reg 2 : ForwardA [1:0] $end
$var reg 2 ; ForwardB [1:0] $end
$upscope $end
$scope task check_test $end
$upscope $end
$scope task set_idle $end
$upscope $end
$upscope $end
$enddefinitions $end
$comment Show the parameter values. $end
$dumpall
$end
#0
$dumpvars
b0 ;
b0 :
09
b0 8
b0 7
b0 6
b0 5
b0 4
b0 3
b0 2
b0 1
b0 0
0/
b0 .
0-
b0 ,
b0 +
b0 *
b0 )
b0 (
0'
b0 &
0%
b0 $
b0 #
0"
0!
$end
#1000
b10 $
b10 :
1%
b101 &
b101 2
b100 *
b100 5
b101 )
b101 4
b1 1
#2000
b10 #
b10 ;
b0 $
b0 :
1%
b101 &
b101 2
b101 *
b101 5
b100 )
b100 4
b10 1
#3000
b0 #
b0 ;
b1 $
b1 :
1-
b11 .
b11 8
0%
b0 &
b0 2
b0 *
b0 5
b11 )
b11 4
b11 1
#4000
b1 #
b1 ;
b0 $
b0 :
b110 *
b110 5
1-
b110 .
b110 8
b0 )
b0 4
b100 1
#5000
b0 #
b0 ;
b10 $
b10 :
1%
b111 &
b111 2
b111 )
b111 4
1-
b111 .
b111 8
b0 *
b0 5
b101 1
#6000
1"
1!
19
b0 $
b0 :
b1000 +
b1000 6
b1000 (
b1000 3
1'
0-
b0 .
b0 8
0%
b0 &
b0 2
b0 )
b0 4
b110 1
#7000
b1000 ,
b1000 7
b0 +
b0 6
1'
b1000 (
b1000 3
b111 1
#8000
0"
0!
09
b0 ,
b0 7
1'
b0 (
b0 3
b1000 1
#9000
1"
1/
0'
b1001 1
#10000
1!
19
b1001 +
b1001 6
b1001 (
b1001 3
1'
1/
b1010 1
#11000
0"
0!
09
b100 .
b100 8
b100 &
b100 2
b100 )
b100 4
0/
b0 +
b0 6
0'
b0 (
b0 3
b1011 1
#12000
b10 #
b10 ;
b1 $
b1 :
1-
1%
b101 *
b101 5
b11 .
b11 8
b101 &
b101 2
b11 )
b11 4
b1100 1
#13000
b1101 1
